allennlp_datalawyer/__init__.py
allennlp_datalawyer/data/__init__.py
allennlp_datalawyer/data/prepare_cp_data.py
allennlp_datalawyer/data/dataset_readers/__init__.py
allennlp_datalawyer/data/dataset_readers/base_json_reader.py
allennlp_datalawyer/data/dataset_readers/cp_relations_reader.py
allennlp_datalawyer/data/dataset_readers/entity_marker.py
allennlp_datalawyer/data/dataset_readers/json_entities_reader.py
allennlp_datalawyer/data/dataset_readers/json_full_relations_reader.py
allennlp_datalawyer/data/dataset_readers/json_relations_reader.py
allennlp_datalawyer/data/dataset_readers/pure_dataset.py
allennlp_datalawyer/data/dataset_readers/relations.py
allennlp_datalawyer/data/token_indexers/__init__.py
allennlp_datalawyer/data/token_indexers/nilc_indexer.py
allennlp_datalawyer/models/__init__.py
allennlp_datalawyer/models/atlop_loss.py
allennlp_datalawyer/models/crf_tagger_head.py
allennlp_datalawyer/models/redn.py
allennlp_datalawyer/models/relations_atlop.py
allennlp_datalawyer/models/relations_classifier.py
allennlp_datalawyer/models/relations_classifier_head.py
allennlp_datalawyer/models/relations_transformers.py
allennlp_datalawyer/predictors/__init__.py
allennlp_datalawyer/predictors/cp_relations_predictor.py
allennlp_datalawyer/predictors/full_relations_predictor.py
allennlp_datalawyer/predictors/relations_predictor.py
allennlp_datalawyer/predictors/sentence_tagger_pt.py
allennlp_datalawyer/tests/__init__.py
allennlp_datalawyer/tune/__init__.py
allennlp_datalawyer/tune/tune_cv.py
allennlp_datalawyer-0.3.18.dist-info/METADATA
allennlp_datalawyer-0.3.18.dist-info/WHEEL
allennlp_datalawyer-0.3.18.dist-info/top_level.txt
allennlp_datalawyer-0.3.18.dist-info/zip-safe
allennlp_datalawyer-0.3.18.dist-info/RECORD
